README.md
setup.py
nemlite/__init__.py
nemlite/declare_names.py
nemlite/engine.py
nemlite/input_generator.py
nemlite/nemlite_defaults.py
nemlite/standards.py
nemlite.egg-info/PKG-INFO
nemlite.egg-info/SOURCES.txt
nemlite.egg-info/dependency_links.txt
nemlite.egg-info/top_level.txt